{
  "introText": "CPMI : Votre partenaire local pour l'installation d'ascenseurs et monte-charges à Moissac, optimisant l'accessibilité de vos bâtiments.",
  "localContext": {
    "title": "Accessibilité à Moissac",
    "content": "La région Occitanie soutient l'accessibilité. CPMI vous accompagne pour adapter vos bâtiments aux normes et bénéficier des aides disponibles pour vos projets."
  },
  "expertAdvice": "Un ascenseur bien installé valorise votre bien immobilier à Moissac.",
  "advantages": [
    "Installation rapide et conforme aux normes locales.",
    "Solutions sur mesure pour tous types de bâtiments.",
    "Maintenance et SAV réactifs en Tarn-et-Garonne."
  ],
  "pricingContext": "Obtenez un devis personnalisé et compétitif pour votre projet à Moissac.",
  "faq": [
    {
      "question": "Normes à Moissac ?",
      "answer": "Conformité aux normes européennes et accessibilité PMR."
    },
    {
      "question": "Délai à Moissac ?",
      "answer": "Devis + installation : délai rapide."
    },
    {
      "question": "SAV local ?",
      "answer": "CPMI assure un SAV rapide et efficace à Moissac."
    }
  ]
}