{
  "introText": "CPMI : Votre partenaire pour l'installation d'ascenseurs et monte-charges à Rambouillet, améliorant l'accessibilité de vos bâtiments.",
  "localContext": {
    "title": "Accessibilité 78",
    "content": "Rambouillet bénéficie d'aides régionales pour l'accessibilité. CPMI vous accompagne dans vos démarches pour l'installation de vos équipements."
  },
  "expertAdvice": "Optimisez l'espace et la conformité avec CPMI.",
  "advantages": [
    "Installation rapide et conforme aux normes à Rambouillet.",
    "Solutions sur mesure pour tous types de bâtiments.",
    "Maintenance et SAV de proximité garantis dans le 78."
  ],
  "pricingContext": "Devis personnalisés et compétitifs pour les professionnels à Rambouillet.",
  "faq": [
    {
      "question": "Ascenseur PMR à Rambouillet ?",
      "answer": "CPMI propose des solutions sur-mesure adaptées PMR."
    },
    {
      "question": "Délai à Rambouillet ?",
      "answer": "Installation rapide selon vos contraintes."
    },
    {
      "question": "SAV ou norme locale ?",
      "answer": "SAV rapide et respect des normes en vigueur."
    }
  ]
}