{
  "introText": "CPMI.fr : Votre expert en installation d'ascenseurs et monte-charges à Vandoeuvre-lès-Nancy, pour une accessibilité optimale.",
  "localContext": {
    "title": "Accessibilité 54",
    "content": "Le Grand Est encourage l'accessibilité PMR. CPMI.fr facilite vos projets d'ascenseurs et monte-charges à Vandoeuvre avec des solutions adaptées."
  },
  "expertAdvice": "CPMI.fr : Des solutions sur-mesure pour bâtiments neufs ou existants.",
  "advantages": [
    "Conformité aux normes d'accessibilité à Vandoeuvre-lès-Nancy.",
    "Installation rapide et professionnelle par des experts locaux.",
    "Solutions personnalisées pour tous types de bâtiments."
  ],
  "pricingContext": "Devis personnalisés et compétitifs pour les professionnels du 54.",
  "faq": [
    {
      "question": "Ascenseur PMR obligatoire ?",
      "answer": "Oui, selon la loi accessibilité."
    },
    {
      "question": "Délai à Vandoeuvre Les Nancy ?",
      "answer": "Variable selon le projet."
    },
    {
      "question": "SAV ou norme locale ?",
      "answer": "SAV rapide et respect des normes en vigueur."
    }
  ]
}