{
  "introText": "CPMI.fr : Votre expert en climatisation tertiaire et industrielle à Briançon, pour un confort optimal toute l'année.",
  "localContext": {
    "title": "Climat Briançonnais & Réglementation",
    "content": "Briançon, avec son climat montagnard, exige des solutions de climatisation performantes. CPMI vous accompagne dans le respect des normes en Provence-Alpes-Côte d'Azur."
  },
  "expertAdvice": "Optimisez votre consommation énergétique avec nos solutions sur-mesure.",
  "advantages": [
    "Installation rapide et efficace à Briançon et ses environs.",
    "Maintenance préventive pour une durée de vie prolongée.",
    "Solutions éco-responsables pour réduire votre empreinte carbone."
  ],
  "pricingContext": "Obtenez un devis personnalisé et compétitif pour votre projet dans le 05.",
  "faq": [
    {
      "question": "Climatisation idéale pour Briançon ?",
      "answer": "Solutions adaptées aux variations climatiques extrêmes."
    },
    {
      "question": "Délai à Briancon ?",
      "answer": "Intervention rapide selon disponibilité."
    },
    {
      "question": "SAV ou norme locale ?",
      "answer": "SAV réactif et respect des normes RT2012 et suivantes."
    }
  ]
}