{
  "introText": "CPMI : Votre expert en climatisation tertiaire et industrielle à Cambrai, pour un confort optimal et une performance énergétique accrue.",
  "localContext": {
    "title": "Climatisation & Cambrai",
    "content": "Le climat variable du Nord nécessite des solutions de climatisation fiables. CPMI vous accompagne pour bénéficier des aides régionales et optimiser votre installation."
  },
  "expertAdvice": "Un audit personnalisé pour une climatisation adaptée à vos besoins spécifiques.",
  "advantages": [
    "Solutions sur-mesure pour bâtiments tertiaires et industriels à Cambrai.",
    "Installation, maintenance et dépannage rapide par des experts.",
    "Réduction de vos coûts énergétiques grâce à des systèmes performants."
  ],
  "pricingContext": "Obtenez un devis personnalisé et compétitif pour votre projet à Cambrai.",
  "faq": [
    {
      "question": "Quelle puissance à Cambrai ?",
      "answer": "CPMI dimensionne selon vos besoins, respectant les normes locales."
    },
    {
      "question": "Délai à Cambrai ?",
      "answer": "Intervention rapide selon urgence."
    },
    {
      "question": "SAV ou norme locale ?",
      "answer": "SAV réactif et respect des normes environnementales en vigueur."
    }
  ]
}