{
  "introText": "CPMI : Votre expert en climatisation tertiaire et industrielle à La Courneuve, pour un confort optimal.",
  "localContext": {
    "title": "Climatisation 93 : Enjeux",
    "content": "La Courneuve subit des étés chauds. Des aides régionales peuvent faciliter l'installation de systèmes performants et économes en énergie pour les entreprises."
  },
  "expertAdvice": "Optimisez votre climatisation pour réduire vos coûts énergétiques.",
  "advantages": [
    "Installation rapide et efficace à La Courneuve.",
    "Maintenance préventive pour éviter les pannes.",
    "Solutions sur mesure pour chaque type de bâtiment."
  ],
  "pricingContext": "Devis personnalisés et prix compétitifs pour les professionnels du 93.",
  "faq": [
    {
      "question": "Quelle puissance pour mes bureaux ?",
      "answer": "Dimensionnement précis selon vos besoins et la surface."
    },
    {
      "question": "Délai à La Courneuve ?",
      "answer": "Intervention rapide."
    },
    {
      "question": "SAV ou norme locale ?",
      "answer": "SAV réactif et respect des normes en vigueur."
    }
  ]
}