{
  "introText": "CPMI.fr : Votre expert en climatisation tertiaire et industrielle à Millau, pour un confort optimal et des économies d'énergie.",
  "localContext": {
    "title": "Climat Millau",
    "content": "Le climat de Millau exige une climatisation performante. Profitez des aides régionales pour l'installation de systèmes éco-énergétiques dans le 12."
  },
  "expertAdvice": "Optimisez votre climatisation pour une efficacité énergétique maximale.",
  "advantages": [
    "Solutions sur-mesure pour les entreprises de Millau et alentours.",
    "Techniciens certifiés pour une installation et maintenance optimales.",
    "Réduction des coûts énergétiques grâce à nos solutions performantes."
  ],
  "pricingContext": "Devis personnalisés et prix compétitifs pour les professionnels du 12.",
  "faq": [
    {
      "question": "Quelle puissance à Millau ?",
      "answer": "Dimensionnement précis selon vos besoins spécifiques."
    },
    {
      "question": "Délai à Millau ?",
      "answer": "Intervention rapide selon disponibilité."
    },
    {
      "question": "Norme ou SAV ?",
      "answer": "Respect des normes et SAV réactif à Millau."
    }
  ]
}