{
  "introText": "CPMI.fr : Votre expert en climatisation tertiaire et industrielle à Plerin (22190), pour un confort optimal et des économies d'énergie.",
  "localContext": {
    "title": "Climat & Solutions à Plerin",
    "content": "Le climat breton exige des solutions de climatisation performantes. CPMI.fr vous accompagne dans vos projets, en tenant compte des spécificités locales et des aides disponibles."
  },
  "expertAdvice": "Optimisez votre climatisation pour une performance durable.",
  "advantages": [
    "Installation rapide et efficace à Plerin et ses environs.",
    "Maintenance préventive pour éviter les pannes coûteuses.",
    "Solutions sur mesure adaptées à vos besoins spécifiques."
  ],
  "pricingContext": "Devis personnalisés et compétitifs pour les professionnels du 22.",
  "faq": [
    {
      "question": "Quelle est la meilleure solution pour mon entreprise à Plerin ?",
      "answer": "CPMI.fr vous conseille sur la solution la plus adaptée."
    },
    {
      "question": "Délai d'intervention à Plerin ?",
      "answer": "Intervention rapide garantie."
    },
    {
      "question": "Normes et SAV CPMI.fr ?",
      "answer": "Respect des normes et SAV réactif à votre service."
    }
  ]
}