{
  "introText": "CPMI : Votre expert en climatisation tertiaire et industrielle à St Junien, pour un confort optimal et une efficacité énergétique accrue.",
  "localContext": {
    "title": "Climatisation 87 : Enjeux Locaux",
    "content": "La Nouvelle-Aquitaine connaît des étés chauds. CPMI vous aide à choisir la solution de climatisation adaptée et à bénéficier des aides régionales."
  },
  "expertAdvice": "Optimisez votre climatisation pour réduire vos coûts énergétiques.",
  "advantages": [
    "Installation rapide et soignée à St Junien et alentours.",
    "Maintenance préventive pour éviter les pannes coûteuses.",
    "Solutions sur-mesure adaptées à vos besoins spécifiques."
  ],
  "pricingContext": "Devis personnalisés et prix compétitifs pour les professionnels du 87.",
  "faq": [
    {
      "question": "Quelle climatisation pour mon entreprise à St Junien ?",
      "answer": "CPMI vous conseille selon vos besoins et votre budget."
    },
    {
      "question": "Délai à St Junien ?",
      "answer": "Intervention rapide, généralement sous 48h."
    },
    {
      "question": "SAV ou norme locale ?",
      "answer": "SAV réactif et respect des normes environnementales locales."
    }
  ]
}