{
  "introText": "CPMI : Votre expert en climatisation tertiaire et industrielle à Tarbes, garantissant confort et performance énergétique.",
  "localContext": {
    "title": "Climatisation à Tarbes",
    "content": "Les étés chauds à Tarbes exigent des solutions de climatisation performantes. Profitez des aides régionales pour optimiser votre installation énergétique."
  },
  "expertAdvice": "Un système bien dimensionné réduit vos coûts énergétiques durablement.",
  "advantages": [
    "Installation rapide et efficace par nos équipes locales.",
    "Solutions adaptées aux spécificités des bâtiments industriels.",
    "Maintenance préventive pour une performance optimale garantie."
  ],
  "pricingContext": "Obtenez un devis personnalisé et compétitif pour votre projet à Tarbes.",
  "faq": [
    {
      "question": "Quelle puissance pour mes locaux ?",
      "answer": "Nous dimensionnons selon vos besoins spécifiques."
    },
    {
      "question": "Délai à Tarbes ?",
      "answer": "Intervention rapide."
    },
    {
      "question": "Maintenance obligatoire ?",
      "answer": "La maintenance assure la conformité et longévité."
    }
  ]
}