{
  "introText": "CPMI.fr facilite l'installation de bornes de recharge pour entreprises et copropriétés à Creil, soutenant la transition énergétique locale.",
  "localContext": {
    "title": "Aides Creil",
    "content": "La région Hauts-de-France encourage l'électromobilité avec des subventions pour les entreprises et copropriétés. CPMI.fr vous guide dans ces démarches à Creil."
  },
  "expertAdvice": "Optimisez votre infrastructure de recharge avec CPMI.fr, expert local.",
  "advantages": [
    "Installation rapide et conforme aux normes à Creil",
    "Solutions sur mesure pour entreprises et copropriétés",
    "Maintenance et SAV assurés par CPMI.fr dans le 60"
  ],
  "pricingContext": "CPMI.fr propose des tarifs compétitifs pour les pros du 60.",
  "faq": [
    {
      "question": "Quelle puissance à Creil ?",
      "answer": "CPMI.fr dimensionne selon vos besoins."
    },
    {
      "question": "Délai à Creil ?",
      "answer": "Installation sous quelques semaines."
    },
    {
      "question": "SAV ou norme locale ?",
      "answer": "SAV rapide et respect des normes IRVE."
    }
  ]
}