{
  "introText": "CPMI facilite l'installation de bornes de recharge pour entreprises et copropriétés à Evreux, soutenant la transition énergétique locale.",
  "localContext": {
    "title": "Bornes à Evreux",
    "content": "La Normandie encourage l'électromobilité. Des aides locales peuvent alléger l'investissement en bornes de recharge pour les entreprises et copropriétés d'Evreux."
  },
  "expertAdvice": "Optimisez votre infrastructure de recharge avec CPMI, expert local.",
  "advantages": [
    "Installation rapide et conforme aux normes à Evreux",
    "Solutions sur mesure pour entreprises et copropriétés",
    "Maintenance et SAV de proximité en Normandie"
  ],
  "pricingContext": "Prix compétitifs et solutions de financement adaptées aux pros du 27.",
  "faq": [
    {
      "question": "Quelle puissance à Evreux ?",
      "answer": "Adaptons la puissance à vos besoins spécifiques."
    },
    {
      "question": "Délai à Evreux ?",
      "answer": "Installation rapide sous quelques semaines."
    },
    {
      "question": "SAV local ?",
      "answer": "SAV rapide et efficace dans tout le 27, garantie CPMI."
    }
  ]
}