{
  "introText": "CPMI.fr facilite l'installation de bornes de recharge pour entreprises et copropriétés à Gerzat, favorisant la mobilité durable.",
  "localContext": {
    "title": "Bornes à Gerzat",
    "content": "La région Auvergne-Rhône-Alpes soutient activement l'électromobilité. Profitez des aides locales pour l'installation de bornes de recharge à Gerzat."
  },
  "expertAdvice": "Optimisez votre infrastructure avec une solution de recharge adaptée et performante.",
  "advantages": [
    "Solution sur mesure pour entreprises et copropriétés à Gerzat.",
    "Installation rapide par des experts certifiés IRVE.",
    "Réduction de l'empreinte carbone et valorisation de votre image."
  ],
  "pricingContext": "Obtenez un devis personnalisé pour votre projet de bornes de recharge dans le Puy-de-Dôme.",
  "faq": [
    {
      "question": "Quelle puissance à Gerzat ?",
      "answer": "Adaptez la puissance à vos besoins et usages spécifiques."
    },
    {
      "question": "Délai à Gerzat ?",
      "answer": "Installation rapide après validation du devis."
    },
    {
      "question": "SAV ou norme locale ?",
      "answer": "SAV réactif et respect des normes en vigueur (IRVE)."
    }
  ]
}