{
  "introText": "CPMI.fr facilite l'installation de bornes de recharge à Pernes Les Fontaines, pour entreprises et copropriétés.",
  "localContext": {
    "title": "Électromobilité 84",
    "content": "La région Provence-Alpes-Côte d'Azur encourage l'électromobilité. CPMI.fr vous guide pour bénéficier des aides locales à Pernes Les Fontaines."
  },
  "expertAdvice": "Optimisez votre transition énergétique avec des solutions adaptées à vos besoins.",
  "advantages": [
    "Installation rapide et professionnelle à Pernes Les Fontaines.",
    "Solutions sur mesure pour entreprises et copropriétés.",
    "Maintenance et SAV assurés par des experts locaux."
  ],
  "pricingContext": "Obtenez un devis personnalisé pour votre projet de bornes de recharge dans le Vaucluse.",
  "faq": [
    {
      "question": "Quelle puissance choisir ?",
      "answer": "CPMI.fr vous conseille selon vos véhicules et usages."
    },
    {
      "question": "Délai à Pernes Les Fontaines ?",
      "answer": "Installation sous quelques semaines."
    },
    {
      "question": "SAV ou norme locale ?",
      "answer": "SAV rapide et conformité aux normes en vigueur."
    }
  ]
}