{
  "introText": "CPMI facilite l'installation de bornes de recharge à Solliès-Pont, un investissement durable pour votre entreprise et copropriété.",
  "localContext": {
    "title": "Transition énergétique à Solliès-Pont",
    "content": "La région Provence-Alpes-Côte d'Azur encourage l'électromobilité. Profitez des aides locales pour l'installation de bornes de recharge."
  },
  "expertAdvice": "Optimisez votre infrastructure avec nos solutions sur-mesure.",
  "advantages": [
    "Valorisation immobilière et attractivité employeur accrue à Solliès-Pont.",
    "Réduction de l'empreinte carbone et engagement RSE.",
    "Solutions de recharge adaptées à tous types de véhicules."
  ],
  "pricingContext": "Nos tarifs sont compétitifs pour les professionnels du Var (83).",
  "faq": [
    {
      "question": "Type de bornes à Solliès-Pont ?",
      "answer": "Bornes standards, accélérées et rapides disponibles."
    },
    {
      "question": "Délai à Sollies Pont ?",
      "answer": "Installation rapide, sous quelques semaines."
    },
    {
      "question": "SAV ou norme locale ?",
      "answer": "SAV réactif et respect des normes en vigueur."
    }
  ]
}