{
  "introText": "CPMI.fr : Installation de bornes de recharge à Saint-Paul, La Réunion, pour entreprises et copropriétés.",
  "localContext": {
    "title": "Transition Énergétique 974",
    "content": "La Réunion encourage l'électromobilité. Profitez des aides régionales pour l'installation de bornes et réduisez votre empreinte carbone sous le soleil réunionnais."
  },
  "expertAdvice": "Optimisez vos infrastructures et attirez une clientèle soucieuse de l'environnement.",
  "advantages": [
    "Valorisation immobilière accrue à Saint-Paul.",
    "Flotte d'entreprise plus verte et économique.",
    "Solution durable pour vos employés et clients."
  ],
  "pricingContext": "Devis personnalisés et compétitifs pour professionnels à La Réunion.",
  "faq": [
    {
      "question": "Bornes compatibles à St Paul ?",
      "answer": "Nous installons toutes les bornes standards."
    },
    {
      "question": "Délai à St Paul ?",
      "answer": "Installation rapide, sous quelques semaines."
    },
    {
      "question": "SAV ou norme locale ?",
      "answer": "SAV local et respect des normes réunionnaises."
    }
  ]
}